hcb_soap_client/__init__.py
hcb_soap_client/account_response.py
hcb_soap_client/hcb_soap_client.py
hcb_soap_client/py.typed
hcb_soap_client/stop_response.py
hcb_soap_client-0.1.2.dist-info/licenses/LICENSE
tests/__init__.py
tests/test_account_response.py
tests/test_hcb_soap_client.py
tests/test_live.py
tests/test_stop_response.py
tests/test_data/__init__.py
tests/test_data/const.py
hcb_soap_client-0.1.2.dist-info/METADATA
hcb_soap_client-0.1.2.dist-info/WHEEL
hcb_soap_client-0.1.2.dist-info/top_level.txt
hcb_soap_client-0.1.2.dist-info/RECORD
