Metadata-Version: 2.4
Name: hcb_soap_client
Version: 0.1.2
Summary: Soap client for Here Comes the Bus
Author-email: Patrick Cartwright <pcartwright1981@gmail.com>
License: MIT
Project-URL: Homepage, https://github.com/pcartwright81/hcb_soap_client
Project-URL: Repository, https://github.com/pcartwright81/hcb_soap_client
Classifier: Programming Language :: Python :: 3
Classifier: License :: OSI Approved :: MIT License
Classifier: Operating System :: OS Independent
Requires-Python: >=3.12
License-File: LICENSE
Requires-Dist: aiohttp==3.13.3
Requires-Dist: pydantic==2.12.2
Requires-Dist: lxml==5.3.0
Requires-Dist: python-dateutil==2.9.0.post0
Provides-Extra: test
Requires-Dist: colorlog==6.10.1; extra == "test"
Requires-Dist: pytest==8.3.4; extra == "test"
Requires-Dist: pytest-asyncio==0.25.3; extra == "test"
Requires-Dist: pytest-cov==6.0.0; extra == "test"
Provides-Extra: dev
Requires-Dist: ruff==0.14.10; extra == "dev"
Dynamic: license-file
